ocrmypdfgui/__init__.py
ocrmypdfgui/__main__.py
ocrmypdfgui/gui.py
ocrmypdfgui/ocr.py
ocrmypdfgui/plugin_progressbar.py
ocrmypdfgui-1.0.1.dist-info/licenses/LICENSE
ocrmypdfgui-1.0.1.dist-info/METADATA
ocrmypdfgui-1.0.1.dist-info/WHEEL
ocrmypdfgui-1.0.1.dist-info/entry_points.txt
ocrmypdfgui-1.0.1.dist-info/top_level.txt
ocrmypdfgui-1.0.1.dist-info/RECORD
