Metadata-Version: 2.4
Name: ocrmypdfgui
Version: 1.0.1
Summary: Hobby Project GUI for the Python Program 'OCRmyPDF' by James R. Barlow
Home-page: https://github.com/alexanderlanganke/ocrmypdfgui
Author: Alexander Langanke
Author-email: alexlanganke@gmail.com
Project-URL: Bug Tracker, https://github.com/alexanderlanganke/ocrmypdfgui/issues
Classifier: Programming Language :: Python :: 3
Classifier: License :: OSI Approved :: MIT License
Classifier: Operating System :: OS Independent
Requires-Python: >=3.6
License-File: LICENSE
Requires-Dist: cffi>=1.9.1
Requires-Dist: coloredlogs>=14.0
Requires-Dist: img2pdf<0.5,>=0.3.0
Requires-Dist: pdfminer.six!=20200720,<=20201018,>=20191110
Requires-Dist: Pillow>=8.1.2
Requires-Dist: pluggy<1.0,>=0.13.0
Requires-Dist: reportlab>=3.5.66
Requires-Dist: setuptools
Requires-Dist: tqdm>=4
Requires-Dist: ocrmypdf<14.0.0,>=13.0.0
Requires-Dist: pikepdf<8.0.0,>=7.2.0
Requires-Dist: pytesseract>=0.3.8
Requires-Dist: PyGObject
Requires-Dist: rarfile>=3.0
Dynamic: author
Dynamic: author-email
Dynamic: classifier
Dynamic: description
Dynamic: description-content-type
Dynamic: home-page
Dynamic: license-file
Dynamic: project-url
Dynamic: requires-dist
Dynamic: requires-python
Dynamic: summary
